sal_xarray/main.py
sal_xarray-0.2.0.dist-info/licenses/LICENSE
sal_xarray-0.2.0.dist-info/METADATA
sal_xarray-0.2.0.dist-info/WHEEL
sal_xarray-0.2.0.dist-info/entry_points.txt
sal_xarray-0.2.0.dist-info/top_level.txt
sal_xarray-0.2.0.dist-info/RECORD
